geotrans/__init__.py
geotrans/cli.py
geotrans/transform.py
geotrans-0.0.5.dist-info/entry_points.txt
geotrans-0.0.5.dist-info/LICENSE.md
geotrans-0.0.5.dist-info/WHEEL
geotrans-0.0.5.dist-info/METADATA
geotrans-0.0.5.dist-info/RECORD
