Metadata-Version: 2.1
Name: geotrans
Version: 0.0.5
Summary: Switch between spatial fileformats.
Home-page: https://github.com/nialov/geotrans
License: MIT
Keywords: data
Author: nialov
Author-email: nikolasovaskainen@gmail.com
Requires-Python: >=3.7.1,<4.0.0
Classifier: License :: OSI Approved :: MIT License
Classifier: Programming Language :: Python :: 3
Classifier: Programming Language :: Python :: 3 :: Only
Classifier: Programming Language :: Python :: 3.8
Classifier: Programming Language :: Python :: 3.9
Classifier: Topic :: Scientific/Engineering :: GIS
Provides-Extra: coverage
Provides-Extra: docs
Provides-Extra: format-lint
Provides-Extra: typecheck
Requires-Dist: black-nb; extra == "format-lint"
Requires-Dist: black; extra == "format-lint"
Requires-Dist: blackdoc; extra == "format-lint"
Requires-Dist: blacken-docs; extra == "format-lint"
Requires-Dist: click
Requires-Dist: coverage-badge; extra == "coverage"
Requires-Dist: coverage; extra == "coverage"
Requires-Dist: geopandas
Requires-Dist: isort; extra == "format-lint"
Requires-Dist: mypy; extra == "typecheck"
Requires-Dist: nbsphinx; extra == "docs"
Requires-Dist: pylint; extra == "format-lint"
Requires-Dist: rstcheck; extra == "format-lint"
Requires-Dist: sphinx-autodoc-typehints; extra == "docs"
Requires-Dist: sphinx-gallery; extra == "docs"
Requires-Dist: sphinx-rtd-theme; extra == "docs"
Requires-Dist: sphinx; extra == "docs" or extra == "format-lint"
Project-URL: Documentation, https://geotrans.readthedocs.io/en/latest/
Project-URL: Repository, https://github.com/nialov/geotrans
